foo_python_module.py
reload_all.py
test_reload_all.py
reload_all-0.6.dist-info/DESCRIPTION.rst
reload_all-0.6.dist-info/METADATA
reload_all-0.6.dist-info/RECORD
reload_all-0.6.dist-info/WHEEL
reload_all-0.6.dist-info/metadata.json
reload_all-0.6.dist-info/top_level.txt
