Metadata-Version: 2.0
Name: reload-all
Version: 0.6
Summary: Reload all modified modules for 2.7 and 3.x
Home-page: https://github.com/fx-kirin/pyreload_all
Author: fx-kirin
Author-email: ono.kirin@gmail.com
License: UNKNOWN
Platform: UNKNOWN
